digurl/cli.py
digurl-0.1.1.dist-info/METADATA
digurl-0.1.1.dist-info/WHEEL
digurl-0.1.1.dist-info/entry_points.txt
digurl-0.1.1.dist-info/RECORD
