Metadata-Version: 2.1
Name: digurl
Version: 0.1.1
Summary: A command line tool to extract domain from URL and perform dig operations
License: MIT
Author: redshwin
Author-email: yongdong.wu@gmail.com
Requires-Python: >=3.7,<4.0
Classifier: License :: OSI Approved :: MIT License
Classifier: Programming Language :: Python :: 3
Classifier: Programming Language :: Python :: 3.7
Classifier: Programming Language :: Python :: 3.8
Classifier: Programming Language :: Python :: 3.9
Classifier: Programming Language :: Python :: 3.10
Classifier: Programming Language :: Python :: 3.11
Classifier: Programming Language :: Python :: 3.12
Classifier: Programming Language :: Python :: 3.13
Requires-Dist: urllib3 (>=2.0.0,<3.0.0)
